{
    "m_Version": 12,
    "DisplayName": "#STR_EXPANSION_MARKET_CATEGORY_GUNS",
    "Icon": "Deliver",
    "Color": "FBFCFEFF",
    "IsExchange": 0,
    "InitStockPercent": 75.0,
    "Items": [
        {
            "ClassName": "makarovij70",
            "MaxPriceThreshold": 200,
            "MinPriceThreshold": 100,
            "SellPricePercent": -1.0,
            "MaxStockThreshold": 100,
            "MinStockThreshold": 1,
            "QuantityPercent": -1,
            "SpawnAttachments": [
                "mag_ij70_8rnd"
            ],
            "Variants": []
        },
        {
            "ClassName": "mag_ij70_8rnd",
            "MaxPriceThreshold": 60,
            "MinPriceThreshold": 30,
            "SellPricePercent": -1.0,
            "MaxStockThreshold": 100,
            "MinStockThreshold": 1,
            "QuantityPercent": -1,
            "SpawnAttachments": [],
            "Variants": []
        },
        {
            "ClassName": "derringer_black",
            "MaxPriceThreshold": 600,
            "MinPriceThreshold": 200,
            "SellPricePercent": -1.0,
            "MaxStockThreshold": 100,
            "MinStockThreshold": 1,
            "QuantityPercent": -1,
            "SpawnAttachments": [],
            "Variants": [
                "derringer_grey",
                "derringer_pink"
            ]
        },
        {
            "ClassName": "colt1911",
            "MaxPriceThreshold": 680,
            "MinPriceThreshold": 340,
            "SellPricePercent": -1.0,
            "MaxStockThreshold": 100,
            "MinStockThreshold": 1,
            "QuantityPercent": -1,
            "SpawnAttachments": [
                "mag_1911_7rnd"
            ],
            "Variants": []
        },
        {
            "ClassName": "mag_1911_7rnd",
            "MaxPriceThreshold": 80,
            "MinPriceThreshold": 40,
            "SellPricePercent": -1.0,
            "MaxStockThreshold": 100,
            "MinStockThreshold": 1,
            "QuantityPercent": -1,
            "SpawnAttachments": [],
            "Variants": []
        }
    ]
}